README.md
mqtt_ws_bridge.py
setup.py
mqtt_ws_bridge.egg-info/PKG-INFO
mqtt_ws_bridge.egg-info/SOURCES.txt
mqtt_ws_bridge.egg-info/dependency_links.txt
mqtt_ws_bridge.egg-info/entry_points.txt
mqtt_ws_bridge.egg-info/requires.txt
mqtt_ws_bridge.egg-info/top_level.txt